Metadata-Version: 1.1
Name: pybson
Version: 0.5.9
Summary: BSON codec for Python
Home-page: http://github.com/py-bson/bson
Author: Ayun Park
Author-email: iamparkayun@gmail.com
License: BSD
Keywords: BSON codec
Platform: Any
Classifier: Programming Language :: Python :: 2.6
Classifier: Programming Language :: Python :: 2.7
Classifier: Programming Language :: Python :: 3.3
Classifier: Programming Language :: Python :: 3.4
Classifier: Programming Language :: Python :: 3.5
Classifier: Programming Language :: Python :: 3.6
